<?xml version="1.0" ?>
<!DOCTYPE PubmedArticleSet PUBLIC "-//NLM//DTD PubMedArticle, 1st January 2023//EN" "https://dtd.nlm.nih.gov/ncbi/pubmed/out/pubmed_230101.dtd">
<PubmedArticleSet>
<PubmedArticle><MedlineCitation Status="MEDLINE" Owner="NLM"><PMID Version="1">31779491</PMID><DateCompleted><Year>2021</Year><Month>03</Month><Day>03</Day></DateCompleted><DateRevised><Year>2021</Year><Month>03</Month><Day>03</Day></DateRevised><Article PubModel="Print-Electronic"><Journal><ISSN IssnType="Electronic">2167-9223</ISSN><JournalIssue CitedMedium="Internet"><Volume>21</Volume><Issue>1-2</Issue><PubDate><Year>2020</Year><Month>Feb</Month></PubDate></JournalIssue><Title>Amyotrophic lateral sclerosis &amp; frontotemporal degeneration</Title><ISOAbbreviation>Amyotroph Lateral Scler Frontotemporal Degener</ISOAbbreviation></Journal><ArticleTitle>ALSUntangled No. 52: Glutathione.</ArticleTitle><Pagination><StartPage>154</StartPage><EndPage>157</EndPage><MedlinePgn>154-157</MedlinePgn></Pagination><ELocationID EIdType="doi" ValidYN="Y">10.1080/21678421.2019.1697029</ELocationID><AuthorList CompleteYN="Y"><Author ValidYN="Y"><CollectiveName>ALSUNTANGLED GROUP</CollectiveName></Author></AuthorList><Language>eng</Language><PublicationTypeList><PublicationType UI="D002363">Case Reports</PublicationType><PublicationType UI="D016428">Journal Article</PublicationType><PublicationType UI="D013485">Research Support, Non-U.S. Gov't</PublicationType></PublicationTypeList><ArticleDate DateType="Electronic"><Year>2019</Year><Month>11</Month><Day>29</Day></ArticleDate></Article><MedlineJournalInfo><Country>England</Country><MedlineTA>Amyotroph Lateral Scler Frontotemporal Degener</MedlineTA><NlmUniqueID>101587185</NlmUniqueID><ISSNLinking>2167-8421</ISSNLinking></MedlineJournalInfo><ChemicalList><Chemical><RegistryNumber>GAN16C9B8O</RegistryNumber><NameOfSubstance UI="D005978">Glutathione</NameOfSubstance></Chemical></ChemicalList><CitationSubset>IM</CitationSubset><MeshHeadingList><MeshHeading><DescriptorName UI="D000690" MajorTopicYN="N">Amyotrophic Lateral Sclerosis</DescriptorName><QualifierName UI="Q000175" MajorTopicYN="N">diagnosis</QualifierName><QualifierName UI="Q000188" MajorTopicYN="Y">drug therapy</QualifierName></MeshHeading><MeshHeading><DescriptorName UI="D018450" MajorTopicYN="N">Disease Progression</DescriptorName></MeshHeading><MeshHeading><DescriptorName UI="D004576" MajorTopicYN="N">Electromyography</DescriptorName><QualifierName UI="Q000187" MajorTopicYN="N">drug effects</QualifierName></MeshHeading><MeshHeading><DescriptorName UI="D005978" MajorTopicYN="N">Glutathione</DescriptorName><QualifierName UI="Q000627" MajorTopicYN="Y">therapeutic use</QualifierName></MeshHeading><MeshHeading><DescriptorName UI="D006801" MajorTopicYN="N">Humans</DescriptorName></MeshHeading><MeshHeading><DescriptorName UI="D008297" MajorTopicYN="N">Male</DescriptorName></MeshHeading><MeshHeading><DescriptorName UI="D008875" MajorTopicYN="N">Middle Aged</DescriptorName></MeshHeading><MeshHeading><DescriptorName UI="D016896" MajorTopicYN="N">Treatment Outcome</DescriptorName></MeshHeading></MeshHeadingList></MedlineCitation><PubmedData><History><PubMedPubDate PubStatus="pubmed"><Year>2019</Year><Month>11</Month><Day>30</Day><Hour>6</Hour><Minute>0</Minute></PubMedPubDate><PubMedPubDate PubStatus="medline"><Year>2021</Year><Month>3</Month><Day>4</Day><Hour>6</Hour><Minute>0</Minute></PubMedPubDate><PubMedPubDate PubStatus="entrez"><Year>2019</Year><Month>11</Month><Day>30</Day><Hour>6</Hour><Minute>0</Minute></PubMedPubDate></History><PublicationStatus>ppublish</PublicationStatus><ArticleIdList><ArticleId IdType="pubmed">31779491</ArticleId><ArticleId IdType="doi">10.1080/21678421.2019.1697029</ArticleId></ArticleIdList></PubmedData></PubmedArticle></PubmedArticleSet>