<?xml version="1.0" ?>
<!DOCTYPE PubmedArticleSet PUBLIC "-//NLM//DTD PubMedArticle, 1st January 2023//EN" "https://dtd.nlm.nih.gov/ncbi/pubmed/out/pubmed_230101.dtd">
<PubmedArticleSet>
<PubmedArticle><MedlineCitation Status="MEDLINE" Owner="NLM"><PMID Version="1">31026532</PMID><DateCompleted><Year>2019</Year><Month>12</Month><Day>23</Day></DateCompleted><DateRevised><Year>2019</Year><Month>12</Month><Day>23</Day></DateRevised><Article PubModel="Print-Electronic"><Journal><ISSN IssnType="Electronic">1872-7972</ISSN><JournalIssue CitedMedium="Internet"><Volume>705</Volume><PubDate><Year>2019</Year><Month>Jul</Month><Day>13</Day></PubDate></JournalIssue><Title>Neuroscience letters</Title><ISOAbbreviation>Neurosci Lett</ISOAbbreviation></Journal><ArticleTitle>Disentangling balance impairments in spinal and bulbar muscular atrophy.</ArticleTitle><Pagination><StartPage>94</StartPage><EndPage>98</EndPage><MedlinePgn>94-98</MedlinePgn></Pagination><ELocationID EIdType="doi" ValidYN="Y">10.1016/j.neulet.2019.04.044</ELocationID><ELocationID EIdType="pii" ValidYN="Y">S0304-3940(19)30286-1</ELocationID><Abstract><AbstractText>Spinal and bulbar muscular atrophy (Kennedy's disease) has been associated with balance dysfunction and falls. However, postural control has not been studied quantitatively. Here, we quantified upright stance and aimed to disentangle the role of vestibular, proprioceptive and oculomotor deficits. Static balance was assessed in Kennedy patients (n&#x2009;=&#x2009;7) during quiet stance on a force platform under different visual and proprioceptive feedback conditions. Vestibular function was assessed with the video head impulse test. Sural nerve neurography was employed to evaluate the severity of peripheral neuropathy. Also, horizontal saccades were recorded and quantified by the main sequence relationship. Posturographic analyses revealed significantly increased body sway, more pronounced in conditions with closed eyes, which was also reflected in the calculated Romberg indices. Horizontal vestibulo-ocular reflex gains were normal, i.e.&#x2009;&gt;&#x2009;0.75. In contrast, compound sensory nerve action potentials were markedly decreased in all patients (mean&#x2009;=&#x2009;2.4&#x2009;&#x3bc;V). Two patients showed slow saccades with increased exponential main sequence constants. We conclude that Kennedy patients exhibit severe deficits in quiet stance. Postural instability is greatest in conditions of absent vision with reduced proprioception being the main determinant of unsteadiness. Some patients show slowed saccadic eye movements suggesting a nuclear abducens neuronopathy.</AbstractText><CopyrightInformation>Copyright &#xa9; 2019 Elsevier B.V. All rights reserved.</CopyrightInformation></Abstract><AuthorList CompleteYN="Y"><Author ValidYN="Y"><LastName>Anagnostou</LastName><ForeName>E</ForeName><Initials>E</Initials><AffiliationInfo><Affiliation>Department of Neurology, University of Athens, Eginition Hospital, Athens, Greece. Electronic address: eanagnost@eginitio.uoa.gr.</Affiliation></AffiliationInfo></Author><Author ValidYN="Y"><LastName>Zachou</LastName><ForeName>A</ForeName><Initials>A</Initials><AffiliationInfo><Affiliation>Department of Neurology, University of Athens, Eginition Hospital, Athens, Greece.</Affiliation></AffiliationInfo></Author><Author ValidYN="Y"><LastName>Breza</LastName><ForeName>M</ForeName><Initials>M</Initials><AffiliationInfo><Affiliation>Department of Neurology, University of Athens, Eginition Hospital, Athens, Greece.</Affiliation></AffiliationInfo></Author><Author ValidYN="Y"><LastName>Kladi</LastName><ForeName>A</ForeName><Initials>A</Initials><AffiliationInfo><Affiliation>Department of Neurology, University of Athens, Eginition Hospital, Athens, Greece.</Affiliation></AffiliationInfo></Author><Author ValidYN="Y"><LastName>Karadima</LastName><ForeName>G</ForeName><Initials>G</Initials><AffiliationInfo><Affiliation>Department of Neurology, University of Athens, Eginition Hospital, Athens, Greece.</Affiliation></AffiliationInfo></Author><Author ValidYN="Y"><LastName>Koutsis</LastName><ForeName>G</ForeName><Initials>G</Initials><AffiliationInfo><Affiliation>Department of Neurology, University of Athens, Eginition Hospital, Athens, Greece.</Affiliation></AffiliationInfo></Author></AuthorList><Language>eng</Language><PublicationTypeList><PublicationType UI="D016428">Journal Article</PublicationType></PublicationTypeList><ArticleDate DateType="Electronic"><Year>2019</Year><Month>04</Month><Day>23</Day></ArticleDate></Article><MedlineJournalInfo><Country>Ireland</Country><MedlineTA>Neurosci Lett</MedlineTA><NlmUniqueID>7600130</NlmUniqueID><ISSNLinking>0304-3940</ISSNLinking></MedlineJournalInfo><CitationSubset>IM</CitationSubset><MeshHeadingList><MeshHeading><DescriptorName UI="D000200" MajorTopicYN="N">Action Potentials</DescriptorName><QualifierName UI="Q000502" MajorTopicYN="N">physiology</QualifierName></MeshHeading><MeshHeading><DescriptorName UI="D000328" MajorTopicYN="N">Adult</DescriptorName></MeshHeading><MeshHeading><DescriptorName UI="D055534" MajorTopicYN="N">Bulbo-Spinal Atrophy, X-Linked</DescriptorName><QualifierName UI="Q000503" MajorTopicYN="Y">physiopathology</QualifierName></MeshHeading><MeshHeading><DescriptorName UI="D016022" MajorTopicYN="N">Case-Control Studies</DescriptorName></MeshHeading><MeshHeading><DescriptorName UI="D006801" MajorTopicYN="N">Humans</DescriptorName></MeshHeading><MeshHeading><DescriptorName UI="D008297" MajorTopicYN="N">Male</DescriptorName></MeshHeading><MeshHeading><DescriptorName UI="D008875" MajorTopicYN="N">Middle Aged</DescriptorName></MeshHeading><MeshHeading><DescriptorName UI="D004856" MajorTopicYN="N">Postural Balance</DescriptorName><QualifierName UI="Q000502" MajorTopicYN="Y">physiology</QualifierName></MeshHeading><MeshHeading><DescriptorName UI="D011434" MajorTopicYN="N">Proprioception</DescriptorName><QualifierName UI="Q000502" MajorTopicYN="Y">physiology</QualifierName></MeshHeading><MeshHeading><DescriptorName UI="D012438" MajorTopicYN="N">Saccades</DescriptorName><QualifierName UI="Q000502" MajorTopicYN="Y">physiology</QualifierName></MeshHeading><MeshHeading><DescriptorName UI="D011984" MajorTopicYN="N">Sensory Receptor Cells</DescriptorName><QualifierName UI="Q000502" MajorTopicYN="N">physiology</QualifierName></MeshHeading><MeshHeading><DescriptorName UI="D013497" MajorTopicYN="N">Sural Nerve</DescriptorName><QualifierName UI="Q000502" MajorTopicYN="N">physiology</QualifierName></MeshHeading><MeshHeading><DescriptorName UI="D015837" MajorTopicYN="N">Vestibular Diseases</DescriptorName><QualifierName UI="Q000503" MajorTopicYN="Y">physiopathology</QualifierName></MeshHeading></MeshHeadingList><KeywordList Owner="NOTNLM"><Keyword MajorTopicYN="N">Balance</Keyword><Keyword MajorTopicYN="N">Kennedy&#x2019;s disease</Keyword><Keyword MajorTopicYN="N">Posturography</Keyword><Keyword MajorTopicYN="N">Spinal and bulbar muscular atrophy</Keyword><Keyword MajorTopicYN="N">Vestibular system</Keyword><Keyword MajorTopicYN="N">motor neuron disease</Keyword></KeywordList></MedlineCitation><PubmedData><History><PubMedPubDate PubStatus="received"><Year>2019</Year><Month>3</Month><Day>6</Day></PubMedPubDate><PubMedPubDate PubStatus="revised"><Year>2019</Year><Month>4</Month><Day>21</Day></PubMedPubDate><PubMedPubDate PubStatus="accepted"><Year>2019</Year><Month>4</Month><Day>22</Day></PubMedPubDate><PubMedPubDate PubStatus="pubmed"><Year>2019</Year><Month>4</Month><Day>27</Day><Hour>6</Hour><Minute>0</Minute></PubMedPubDate><PubMedPubDate PubStatus="medline"><Year>2019</Year><Month>12</Month><Day>24</Day><Hour>6</Hour><Minute>0</Minute></PubMedPubDate><PubMedPubDate PubStatus="entrez"><Year>2019</Year><Month>4</Month><Day>27</Day><Hour>6</Hour><Minute>0</Minute></PubMedPubDate></History><PublicationStatus>ppublish</PublicationStatus><ArticleIdList><ArticleId IdType="pubmed">31026532</ArticleId><ArticleId IdType="doi">10.1016/j.neulet.2019.04.044</ArticleId><ArticleId IdType="pii">S0304-3940(19)30286-1</ArticleId></ArticleIdList></PubmedData></PubmedArticle></PubmedArticleSet>